poodle_async_mini/__init__.py
poodle_async_mini/api_client.py
poodle_async_mini/api_response.py
poodle_async_mini/configuration.py
poodle_async_mini/exceptions.py
poodle_async_mini/py.typed
poodle_async_mini/rest.py
poodle_async_mini/api/__init__.py
poodle_async_mini/api/default_api.py
poodle_async_mini/models/__init__.py
poodle_async_mini/models/core_comment_add_comments_parameters_comments_inner.py
poodle_async_mini/models/core_comment_add_comments_response_inner.py
poodle_async_mini/models/core_comment_get_comments_response.py
poodle_async_mini/models/core_comment_get_comments_response_warnings_inner.py
poodle_async_mini/models/core_course_get_contents_parameters_options_inner.py
poodle_async_mini/models/core_course_get_contents_response_inner.py
poodle_async_mini/models/core_course_get_contents_response_inner_modules_inner.py
poodle_async_mini/models/core_course_get_contents_response_inner_modules_inner_activitybadge.py
poodle_async_mini/models/core_course_get_contents_response_inner_modules_inner_activitybadge_one_of.py
poodle_async_mini/models/core_course_get_contents_response_inner_modules_inner_activitybadge_one_of_badgeextraattributes_inner.py
poodle_async_mini/models/core_course_get_contents_response_inner_modules_inner_completiondata.py
poodle_async_mini/models/core_course_get_contents_response_inner_modules_inner_completiondata_details_inner.py
poodle_async_mini/models/core_course_get_contents_response_inner_modules_inner_completiondata_details_inner_rulevalue.py
poodle_async_mini/models/core_course_get_contents_response_inner_modules_inner_contents_inner.py
poodle_async_mini/models/core_course_get_contents_response_inner_modules_inner_contents_inner_tags_inner.py
poodle_async_mini/models/core_course_get_contents_response_inner_modules_inner_contentsinfo.py
poodle_async_mini/models/core_course_get_contents_response_inner_modules_inner_dates_inner.py
poodle_async_mini/models/core_enrol_get_users_courses_response_inner.py
poodle_async_mini-5.0.3.dist-info/METADATA
poodle_async_mini-5.0.3.dist-info/WHEEL
poodle_async_mini-5.0.3.dist-info/top_level.txt
poodle_async_mini-5.0.3.dist-info/RECORD
