Metadata-Version: 2.4
Name: poodle_async_mini
Version: 5.0.3
Summary: Moodle Webservice API
Author-email: OpenAPI Generator Community <team@openapitools.org>
Project-URL: Repository, https://github.com/bchmnn/poodle
Keywords: OpenAPI,OpenAPI-Generator,Moodle Webservice API
Requires-Python: >=3.9
Requires-Dist: urllib3<3.0.0,>=2.1.0
Requires-Dist: python-dateutil>=2.8.2
Requires-Dist: aiohttp>=3.8.4
Requires-Dist: aiohttp-retry>=2.8.3
Requires-Dist: pydantic>=2
Requires-Dist: typing-extensions>=4.7.1
Requires-Dist: lazy-imports<2,>=1
